datosgcba_docs/__init__.py
datosgcba_docs/main.html
datosgcba_docs/mkdocs_theme.yml
datosgcba_docs/assets/fonts/CHANEWEI.eot
datosgcba_docs/assets/fonts/CHANEWEI.svg
datosgcba_docs/assets/fonts/CHANEWEI.ttf
datosgcba_docs/assets/fonts/CHANEWEI.woff
datosgcba_docs/assets/fonts/bastrap-icons.eot
datosgcba_docs/assets/fonts/bastrap-icons.svg
datosgcba_docs/assets/fonts/bastrap-icons.ttf
datosgcba_docs/assets/fonts/bastrap-icons.woff
datosgcba_docs/assets/fonts/glyphicons-halflings-regular.eot
datosgcba_docs/assets/fonts/glyphicons-halflings-regular.svg
datosgcba_docs/assets/fonts/glyphicons-halflings-regular.ttf
datosgcba_docs/assets/fonts/glyphicons-halflings-regular.woff
datosgcba_docs/assets/images/favicon.png
datosgcba_docs/assets/images/icons/github.f0b8504a.svg
datosgcba_docs/assets/images/logos/ba-header-vb.svg
datosgcba_docs/assets/images/logos/ba-header.svg
datosgcba_docs/assets/images/logos/ba_logo.png
datosgcba_docs/assets/images/logos/ba_vamosba_blanco.png
datosgcba_docs/assets/images/logos/logo-area.png
datosgcba_docs/assets/images/logos/logo-bac.svg
datosgcba_docs/assets/images/social/social-fb.png
datosgcba_docs/assets/images/social/social-fb.svg
datosgcba_docs/assets/images/social/social-fl.png
datosgcba_docs/assets/images/social/social-fl.svg
datosgcba_docs/assets/images/social/social-gp.png
datosgcba_docs/assets/images/social/social-gp.svg
datosgcba_docs/assets/images/social/social-in.png
datosgcba_docs/assets/images/social/social-in.svg
datosgcba_docs/assets/images/social/social-rss.png
datosgcba_docs/assets/images/social/social-rss.svg
datosgcba_docs/assets/images/social/social-tw.png
datosgcba_docs/assets/images/social/social-tw.svg
datosgcba_docs/assets/images/social/social-yt.png
datosgcba_docs/assets/images/social/social-yt.svg
datosgcba_docs/assets/javascripts/application.583bbe55.js
datosgcba_docs/assets/javascripts/modernizr.1aa3b519.js
datosgcba_docs/assets/javascripts/lunr/lunr.da.js
mkdocs_datosgcba-1.0.3.dist-info/DESCRIPTION.rst
mkdocs_datosgcba-1.0.3.dist-info/METADATA
mkdocs_datosgcba-1.0.3.dist-info/RECORD
mkdocs_datosgcba-1.0.3.dist-info/WHEEL
mkdocs_datosgcba-1.0.3.dist-info/entry_points.txt
mkdocs_datosgcba-1.0.3.dist-info/metadata.json
mkdocs_datosgcba-1.0.3.dist-info/top_level.txt
