Metadata-Version: 2.0
Name: mkdocs-datosgcba
Version: 1.0.3
Summary: Temas de datosgcba para documentación con MkDocs
Home-page: http://www.mkdocs.org
Author: Buenos Aires Data
Author-email: gobiernoabierto@buenosaires.gob.ar
License: BSD
Platform: UNKNOWN
